ShuiwuXingyeShujuZhinenghuaJiejuefangan/README.md
ShuiwuXingyeShujuZhinenghuaJiejuefangan/__init__.py
ShuiwuXingyeShujuZhinenghuaJiejuefangan/__main__.py
ShuiwuXingyeShujuZhinenghuaJiejuefangan/file.pdf
ShuiwuXingyeShujuZhinenghuaJiejuefangan/index.html
shuiwu_xingye_shuju_zhinenghua_jiejuefangan-2024.3.6.0.dist-info/METADATA
shuiwu_xingye_shuju_zhinenghua_jiejuefangan-2024.3.6.0.dist-info/WHEEL
shuiwu_xingye_shuju_zhinenghua_jiejuefangan-2024.3.6.0.dist-info/entry_points.txt
shuiwu_xingye_shuju_zhinenghua_jiejuefangan-2024.3.6.0.dist-info/top_level.txt
shuiwu_xingye_shuju_zhinenghua_jiejuefangan-2024.3.6.0.dist-info/RECORD
